random_forest/__init__.py
random_forest/enhancer.py
ai_query_enhancer-0.1.4.dist-info/METADATA
ai_query_enhancer-0.1.4.dist-info/WHEEL
ai_query_enhancer-0.1.4.dist-info/top_level.txt
ai_query_enhancer-0.1.4.dist-info/RECORD
